{
    "name": "bosonKit",
    "version": "4.0.5",
    "description": "DFRobot Boson Kit is a set of coding-free electronic building blocks for young inventors, STEM educators and tinkerers.",
    "license": "MIT",
    "dependencies": {
        "core": "*",
        "ws2812b": "github:microsoft/pxt-ws2812b#v0.1.2"
    },
    "files": [
        "README.md",
        "bosonKit.ts",
        "_locales/zh-cn/bosonKit-strings.json",
        "_locales/zh-cn/bosonKit-jsdoc-strings.json",
        "_locales/ru/bosonKit-strings.json",
        "_locales/ru/bosonKit-jsdoc-strings.json"
    ],
    "testFiles": [
        "test.ts"
    ],
    "targetVersions": {
        "target": "5.0.12",
        "targetId": "microbit"
    },
    "supportedTargets": [
        "microbit"
    ],
    "preferredEditor": "tsprj"
}
